swagger_tester/__init__.py
swagger_tester/swagger_tester.py
swagger_tester-0.2.12.dist-info/METADATA
swagger_tester-0.2.12.dist-info/RECORD
swagger_tester-0.2.12.dist-info/WHEEL
swagger_tester-0.2.12.dist-info/top_level.txt
