Metadata-Version: 1.1
Name: swagger_tester
Version: 0.2.12
Summary: Automatically test your swagger API
Home-page: https://github.com/Trax-air/swagger-tester
Author: Cyprien Guillemot
Author-email: cyprien.guillemot@gmail.com
License: MIT
Keywords: swagger,tester,API,REST,swagger-tester
Platform: UNKNOWN
Classifier: Development Status :: 5 - Production/Stable
Classifier: Intended Audience :: Developers
Classifier: License :: OSI Approved :: MIT License
Classifier: Natural Language :: English
Classifier: Programming Language :: Python :: 2
Classifier: Programming Language :: Python :: 2.7
Classifier: Programming Language :: Python :: 3
Classifier: Programming Language :: Python :: 3.4
